apis_bibsonomy/__init__.py
apis_bibsonomy/admin.py
apis_bibsonomy/api_views.py
apis_bibsonomy/apps.py
apis_bibsonomy/autocompletes.py
apis_bibsonomy/forms.py
apis_bibsonomy/models.py
apis_bibsonomy/serializers.py
apis_bibsonomy/urls.py
apis_bibsonomy/utils.py
apis_bibsonomy/views.py
apis_bibsonomy/management/commands/updatebibtex.py
apis_bibsonomy/migrations/0001_initial.py
apis_bibsonomy/migrations/0002_reference_folio.py
apis_bibsonomy/migrations/0003_auto_20230202_0953.py
apis_bibsonomy/migrations/0004_alter_reference_bibtex.py
apis_bibsonomy/migrations/__init__.py
apis_bibsonomy/static/apis_bibsonomy/css/apis_bibsonomy.css
apis_bibsonomy/static/css/apis_bibsonomy.css
apis_bibsonomy/static/js/apis_bibsonomy.js
apis_bibsonomy/templates/base.html
apis_bibsonomy/templates/apis_bibsonomy/link_to_reference_on_tag.html
apis_bibsonomy/templates/apis_bibsonomy/reference_confirm_delete.html
apis_bibsonomy/templates/apis_bibsonomy/reference_detail.html
apis_bibsonomy/templates/apis_bibsonomy/reference_form.html
apis_bibsonomy/templates/apis_bibsonomy/reference_list.html
apis_bibsonomy/templates/apis_bibsonomy/partials/reference_list.html
apis_bibsonomy/templatetags/__init__.py
apis_bibsonomy/templatetags/bibsonomy_templatetags.py
apis_bibsonomy-0.13.2.dist-info/METADATA
apis_bibsonomy-0.13.2.dist-info/WHEEL
apis_bibsonomy-0.13.2.dist-info/licenses/LICENSE.txt
apis_bibsonomy-0.13.2.dist-info/RECORD
