Metadata-Version: 2.4
Name: apis-bibsonomy
Version: 0.13.2
Summary: Bibsonomy/Zotero plugin for managing refernces in APIS framework
Author-email: Matthias Schlögl <m.schloegl@gmail.com>
License-Expression: MIT
License-File: LICENSE.txt
Requires-Python: >=3.11
Requires-Dist: django-autocomplete-light>=3.11.0
Requires-Dist: django-crispy-forms>=2.1
Requires-Dist: django>=3.0
Requires-Dist: djangorestframework>=3.15.1
Requires-Dist: jmespath>=0.10.0
Requires-Dist: requests>=2.32.3
